{
    "id": 132395401,
    "name": "easy phonk 1",
    "author": "barcode",
    "creators": ["barcode"],
    "verifier": "barcode scanner",
    "verification": "https://youtu.be/lbChKUlLFN8",
    "percentToQualify": "100",
    "password": "Free To Copy",
     "records": [
        {
            "user": "bigbadbarry1",
            "link": "dih",
            "percent": 100,
            "hz": 60
        },
            {
            "user": "andy",
            "link": "https://drive.google.com/file/d/1H9XhaTLBJGDLJN2qkvf6mpw66y9-KpJY/view",
            "percent": 100,
            "hz": 165
         },
            {
            "user": "pillow",
            "link": "https://drive.google.com/file/d/1eb6S_4xWuGpjQLitr4mMZwnFlCOkUQPF/view?usp=sharing",
            "percent": 100,
            "hz": 144
        }
    ]
}
